grouping_sizePkg/__init__.py
grouping_sizePkg/grouping_sizePkg.py
grouping_sizePkg-0.0.4.dist-info/LICENSE
grouping_sizePkg-0.0.4.dist-info/METADATA
grouping_sizePkg-0.0.4.dist-info/WHEEL
grouping_sizePkg-0.0.4.dist-info/top_level.txt
grouping_sizePkg-0.0.4.dist-info/RECORD
